MANIFEST.in
README.rst
setup.py
src/strippers/__init__.py
src/strippers/facebook/MultipartPostHandler.py
src/strippers/facebook/__init__.py
src/strippers/facebook/error.py
src/strippers/facebook/graphapi.py
src/strippers/facebook/graphobject.py
src/strippers/facebook/permission.py
src/strippers/facebook/rest.py
src/strippers/facebook/testuser.py
src/strippers/facebook/util.py
strippers.facebook.egg-info/PKG-INFO
strippers.facebook.egg-info/SOURCES.txt
strippers.facebook.egg-info/dependency_links.txt
strippers.facebook.egg-info/namespace_packages.txt
strippers.facebook.egg-info/not-zip-safe
strippers.facebook.egg-info/requires.txt
strippers.facebook.egg-info/top_level.txt