Metadata-Version: 1.0
Name: strippers.facebook
Version: 0.9b
Summary: Python library for Facebook Graph API
Home-page: http://pypi.python.org/pypi/strippers.facebook
Author: Tomohiro Otsuka
Author-email: t.otsuka@gmail.com
License: UNKNOWN
Keywords: Facebook oauth
Platform: UNKNOWN
Classifier: Development Status :: 4 - Beta
Classifier: Intended Audience :: Developers
Classifier: Topic :: Software Development :: Libraries :: Python Modules
Classifier: Operating System :: OS Independent
Classifier: Natural Language :: Japanese
